{
  "year": 2026,
  "mode": "bootstrap",
  "selected_plants": [
    "Tomatoes",
    "Corn",
    "Onions",
    "Cucumbers",
    "Lettuce",
    "Radish"
  ],
  "timeline": {
    "1": [
      {
        "plant": "Radish",
        "start": "2026-02-01",
        "end": "2026-03-03",
        "method": "direct_sow"
      },
      {
        "plant": "Tomatoes",
        "start": "2026-04-15",
        "end": "2026-07-24",
        "method": "transplant"
      }
    ],
    "2": [
      {
        "plant": "Lettuce",
        "start": "2026-03-15",
        "end": "2026-05-04",
        "method": "transplant"
      },
      {
        "plant": "Corn",
        "start": "2026-05-15",
        "end": "2026-08-08",
        "method": "direct_sow"
      }
    ]
  },
  "assigned": [
    {
      "plant": "Tomatoes",
      "plot_id": 1,
      "start": "2026-04-15",
      "end": "2026-07-24",
      "method": "transplant"
    },
    {
      "plant": "Corn",
      "plot_id": 2,
      "start": "2026-05-15",
      "end": "2026-08-08",
      "method": "direct_sow"
    },
    {
      "plant": "Lettuce",
      "plot_id": 2,
      "start": "2026-03-15",
      "end": "2026-05-04",
      "method": "transplant"
    },
    {
      "plant": "Radish",
      "plot_id": 1,
      "start": "2026-02-01",
      "end": "2026-03-03",
      "method": "direct_sow"
    }
  ],
  "unassigned_plants": [
    "Onions",
    "Cucumbers"
  ],
  "adjacency_events": [
    {
      "plot_a": 1,
      "plot_b": 2,
      "plant_a": "Tomatoes",
      "plant_b": "Lettuce",
      "overlap_start": "2026-04-15",
      "overlap_end": "2026-05-04",
      "compatibility": 1
    },
    {
      "plot_a": 1,
      "plot_b": 2,
      "plant_a": "Tomatoes",
      "plant_b": "Corn",
      "overlap_start": "2026-05-15",
      "overlap_end": "2026-07-24",
      "compatibility": -3
    }
  ],
  "score": -2
}